setup.py
pkgsync/__init__.py
pkgsync/digest.py
pkgsync/dist.py
pkgsync/exceptions.py
pkgsync/meta.py
pkgsync/repo.py
pkgsync/status.py
pkgsync/sync.py
pkgsync/upload.py
pkgsync/util.py
pkgsync/versions.py
pkgsync.egg-info/PKG-INFO
pkgsync.egg-info/SOURCES.txt
pkgsync.egg-info/dependency_links.txt
pkgsync.egg-info/entry_points.txt
pkgsync.egg-info/not-zip-safe
pkgsync.egg-info/requires.txt
pkgsync.egg-info/top_level.txt