Metadata-Version: 1.0
Name: pkgsync
Version: 0.1.0
Summary: Synchronise packages between two python software repositories
Home-page: UNKNOWN
Author: Alex Holmes
Author-email: alex.holmes@isotoma.com
License: UNKNOWN
Platform: UNKNOWN
